vpe/__init__.py
vpe/app_ui_support.py
vpe/channels.py
vpe/colors.py
vpe/common.py
vpe/config.py
vpe/core.py
vpe/diffs.py
vpe/install.py
vpe/mapping.py
vpe/message_bus.py
vpe/panels.py
vpe/py.typed
vpe/rich_support.py
vpe/rpy_support.py
vpe/rpyc_support.py
vpe/syntax.py
vpe/ui.py
vpe/user_commands.py
vpe/utils.py
vpe/vim.pyi
vpe/vpe_commands.py
vpe/windows.py
vpe/wrappers.py
vpe/minirpyc/__init__.py
vpe/minirpyc/core/__init__.py
vpe/minirpyc/core/brine.py
vpe/minirpyc/core/consts.py
vpe/minirpyc/core/netref.py
vpe/minirpyc/core/protocol.py
vpe/minirpyc/core/service.py
vpe/minirpyc/core/vinegar.py
vpe/minirpyc/lib/__init__.py
vpe/minirpyc/lib/colls.py
vpe/minirpyc/utils/__init__.py
vpe/minirpyc/utils/classic.py
vpe/minirpyc/utils/helpers.py
vpe/resources/000-vpe.vim
vpe/resources/vpe-help.txt
vpe-0.7.3.dist-info/licenses/LICENCE
vpe-0.7.3.dist-info/METADATA
vpe-0.7.3.dist-info/WHEEL
vpe-0.7.3.dist-info/top_level.txt
vpe-0.7.3.dist-info/RECORD
