Metadata-Version: 2.4
Name: vpe
Version: 0.7.3
Summary: The Vim Python Extensions (VPE)
Author-email: Paul Ollis <paul@cleversheep.org>
License-Expression: MIT
Project-URL: Homepage, https://github.com/paul-ollis/vim-vpe
Project-URL: Bug Tracker, https://github.com/paul-ollis/vim-vpe/issues
Project-URL: Documentation, https://vim-vpe.readthedocs.io
Classifier: Development Status :: 3 - Alpha
Classifier: Operating System :: POSIX :: Linux
Classifier: Programming Language :: Python :: 3
Classifier: Programming Language :: Python :: 3.11
Classifier: Environment :: Console
Classifier: Topic :: Education
Requires-Python: <3.14,>=3.11
License-File: LICENCE
Provides-Extra: test
Provides-Extra: docs
Requires-Dist: sphinx_rtd_theme; extra == "docs"
Dynamic: license-file
